pitagaccess/__init__.py
pitagaccess-0.1.dist-info/LICENSE.txt
pitagaccess-0.1.dist-info/METADATA
pitagaccess-0.1.dist-info/WHEEL
pitagaccess-0.1.dist-info/top_level.txt
pitagaccess-0.1.dist-info/RECORD
