Metadata-Version: 2.1
Name: pitagaccess
Version: 0.1
Summary: This is PI TAGS Access Package
Author: Patiwa Danny Mhango
Author-email: patiwadannymhango@outlook.com
Classifier: Programming Language :: Python :: 3
Classifier: License :: OSI Approved :: MIT License
Classifier: Operating System :: OS Independent
License-File: LICENSE.txt
